vidstream/__init__.py
vidstream/audio.py
vidstream/streaming.py
byfron-0.0.13.dist-info/LICENSE
byfron-0.0.13.dist-info/METADATA
byfron-0.0.13.dist-info/WHEEL
byfron-0.0.13.dist-info/top_level.txt
byfron-0.0.13.dist-info/RECORD
